{
	"name" : "John Q. Public"
	"company" : "UberTech Inc."
	"title" : "Chief Bottle Washer"
	"photo" : "/path/to/photo.jpg",
	 "file_metrics_dont_edit_these" : 
		{
		"work_length_in_hours": 4.0,
		"total_amount_worked" : 3.0,
		"efficiency" : 75.0,
		"number_work_events" : 5,
		"number_break_events" : 8,
		"number_bubble_events" : 5,
		"number_regions" : 5
		}
	"event" :
		[
			{
				"type" : "work",
				"length_in_secs" : 5,
				"post_it_text": "Work #1",
				"speech_bubble": "Getting started now."
			},
			{
				"type" : "break",
				"length_in_secs" : 4,
				"post_it_text" : "Break #1"
				"speech_bubble": "Have to go potty."
			}
			{
				"type" : "work",
				"length_in_secs" : 5,
				"post_it_text" : "Work #2"
				"speech_bubble": "Starting up again."
			}
			{
				"type" : "break",
				"length_in_secs" : 4,
				"post_it_text" : "Break #2"
				"speech_bubble": "Going to walk around."
			}
			{
				"type" : "work",
				"length_in_secs" : 5,
				"post_it_text" : "Work #3"
				"speech_bubble": "Let's do this."
			}
			{
				"type" : "break",
				"length_in_secs" : 4,
				"post_it_text" : "Break #3"
				"speech_bubble": "Let's jog!"
			}
			{
				"type" : "work",
				"length_in_secs" : 5,
				"post_it_text" : "Work #4"
				"speech_bubble": "Last work block."
			}
			{
				"type" : "break",
				"length_in_secs" : 4,
				"post_it_text" : "Done for the day"
				"speech_bubble": "I'm done for today!"
			}
		]
}